pyflange/__init__.py
pyflange/bolts.py
pyflange/fatigue.py
pyflange/flangesegments.py
pyflange/gap.py
pyflange/stats.py
pyflange/utils.py
pyflange/data/bolts.flat_washers.csv
pyflange/data/bolts.hex_nuts.csv
pyflange/data/bolts.materials.csv
pyflange/data/bolts.metric_screws.csv
pyflange/data/bolts.round_nuts.csv
pyflange/data/flangesegments.shell_stiffness.csv
pyflange-0.9.1.dist-info/METADATA
pyflange-0.9.1.dist-info/WHEEL
pyflange-0.9.1.dist-info/licenses/LICENSE
pyflange-0.9.1.dist-info/RECORD
