Metadata-Version: 2.4
Name: pyflange
Version: 0.9.1
Summary: A set of tools for designing large flanges.
Project-URL: Homepage, https://github.com/kcibv/pyflange
Project-URL: Issues, https://github.com/kcibv/pyflange/issues
Author-email: Marcello Del Buono <m.buono@kci.nl>
License-Expression: GPL-3.0-only
License-File: LICENSE
Classifier: License :: OSI Approved :: GNU General Public License v3 (GPLv3)
Classifier: Operating System :: OS Independent
Classifier: Programming Language :: Python :: 3
Requires-Python: >=3.9
Requires-Dist: numpy>=1.26.4
Requires-Dist: pandas
Requires-Dist: scipy
